fuzzy_ads/__init__.py
fuzzy_ads/cli.py
fuzzy_ads/query.py
fuzzy_ads-0.1.13.dist-info/LICENSE
fuzzy_ads-0.1.13.dist-info/METADATA
fuzzy_ads-0.1.13.dist-info/WHEEL
fuzzy_ads-0.1.13.dist-info/entry_points.txt
fuzzy_ads-0.1.13.dist-info/RECORD
