Metadata-Version: 2.1
Name: fuzzy-ads
Version: 0.1.13
Summary: Unofficial Command Line Interface the SAO/NASA Astrophysics Data System
Home-page: https://github.com/maxmahlke/fuzzy-ads
Author: Max Mahlke
Author-email: max.mahlke@oca.eu
Requires-Python: >=3.7
Classifier: Programming Language :: Python :: 3
Classifier: Programming Language :: Python :: 3.7
Classifier: Programming Language :: Python :: 3.8
Classifier: Programming Language :: Python :: 3.9
Classifier: Programming Language :: Python :: 3.10
Classifier: Programming Language :: Python :: 3.11
Requires-Dist: ads (>=0.12.3)
Requires-Dist: click (>=8.0.4)
Requires-Dist: requests (>=2.27.1)
Requires-Dist: rich (>=11.2.0)
Project-URL: Documentation, https://github.com/maxmahlke/fuzzy-ads
Project-URL: Repository, https://github.com/maxmahlke/fuzzy-ads.git
